stochastic_py-0.10.5.dist-info/METADATA
stochastic_py-0.10.5.dist-info/WHEEL
stochastic_rs/__init__.py
stochastic_rs/stochastic_rs.abi3.so
stochastic_py-0.10.5.dist-info/RECORD
