Metadata-Version: 2.3
Name: stochastic-py
Version: 0.10.5
Classifier: Programming Language :: Rust
Classifier: Programming Language :: Python :: Implementation :: CPython
Classifier: Programming Language :: Python :: Implementation :: PyPy
Summary: A Rust library for quant finance and simulating stochastic processes.
Keywords: stochastic,quant,finance,simulation,statistics
Home-Page: https://github.com/dancixx/stochastic-rs
License: MIT
Requires-Python: >=3.8
Project-URL: Source Code, https://github.com/dancixx/stochastic-rs
